starlite_users/__init__.py
starlite_users/adapter/sqlalchemy/guid.py
starlite_users/adapter/sqlalchemy/mixins.py
starlite_users/adapter/sqlalchemy/repository.py
starlite_users/config.py
starlite_users/dependencies.py
starlite_users/exceptions.py
starlite_users/generics.py
starlite_users/guards.py
starlite_users/main.py
starlite_users/password.py
starlite_users/route_handlers.py
starlite_users/schema.py
starlite_users/service.py
starlite_users/user_handlers.py
starlite_users-0.8.1.dist-info/LICENSE
starlite_users-0.8.1.dist-info/METADATA
starlite_users-0.8.1.dist-info/WHEEL
starlite_users-0.8.1.dist-info/RECORD
