Metadata-Version: 2.1
Name: starlite-users
Version: 0.8.1
Summary: Authentication and user management for Starlite
License: MIT
Author: Michael Bosch
Author-email: michael@lonelyviking.com
Requires-Python: >=3.8,<4.0
Classifier: License :: OSI Approved :: MIT License
Classifier: Programming Language :: Python :: 3
Classifier: Programming Language :: Python :: 3.8
Classifier: Programming Language :: Python :: 3.9
Classifier: Programming Language :: Python :: 3.10
Classifier: Programming Language :: Python :: 3.11
Classifier: Programming Language :: Python :: 3.12
Requires-Dist: argon2-cffi
Requires-Dist: cryptography
Requires-Dist: passlib
Requires-Dist: python-jose
Requires-Dist: sqlalchemy
Requires-Dist: starlite
